yvi/__init__.py
yvi/exceptions.py
yvi/yvi.py
yvi/config/__init__.py
yvi/util/__init__.py
yvi-0.0.4.dist-info/LICENSE
yvi-0.0.4.dist-info/METADATA
yvi-0.0.4.dist-info/WHEEL
yvi-0.0.4.dist-info/top_level.txt
yvi-0.0.4.dist-info/RECORD
