Metadata-Version: 2.1
Name: yvi
Version: 0.0.4
Summary: Retrieve youtube video info.
Home-page: https://github.com/taizan-hokuto/yvi
Author: taizan-hokuto
Author-email: 55448286+taizan-hokuto@users.noreply.github.com
License: MIT
Keywords: youtube
Platform: UNKNOWN
Classifier: Natural Language :: Japanese
Classifier: Development Status :: 4 - Beta
Classifier: Programming Language :: Python
Classifier: Programming Language :: Python :: 3.7
Classifier: Programming Language :: Python :: 3.8
Classifier: License :: OSI Approved :: MIT License
Requires-Dist: requests
Requires-Dist: emoji
